python_signal/__init__.py
python_signal/signal.py
python_signal-0.0.2.dist-info/LICENSE
python_signal-0.0.2.dist-info/METADATA
python_signal-0.0.2.dist-info/WHEEL
python_signal-0.0.2.dist-info/top_level.txt
python_signal-0.0.2.dist-info/RECORD
