Metadata-Version: 2.1
Name: python-signal
Version: 0.0.2
Summary: Python Signal Event Python package
Home-page: https://github.com/blueromans/PythonSignal.git
Author: Yaşar Özyurt
Author-email: blueromans@gmail.com
Project-URL: Bug Tracker, https://github.com/blueromans/PythonSignal/issues
Classifier: Programming Language :: Python :: 3
Classifier: License :: OSI Approved :: MIT License
Classifier: Operating System :: OS Independent
Requires-Python: >=3.6
License-File: LICENSE
